web3storage/__init__.py
web3storage-0.1.1.dist-info/WHEEL
web3storage-0.1.1.dist-info/METADATA
web3storage-0.1.1.dist-info/RECORD
